linkymeter/__init__.py
linkymeter/web/__init__.py
linkymeter/web/datashaper.py
linkymeter/web/session.py
linkymeter-1.0.0.dist-info/LICENSE
linkymeter-1.0.0.dist-info/LICENSE.LESSER
linkymeter-1.0.0.dist-info/METADATA
linkymeter-1.0.0.dist-info/WHEEL
linkymeter-1.0.0.dist-info/top_level.txt
linkymeter-1.0.0.dist-info/RECORD
