Metadata-Version: 2.1
Name: linkymeter
Version: 1.0.0
Summary: Get Enedis smart meter (linky) data from Enedis webserver
Home-page: https://gitlab.com/ermitz/linkymeter
Author: ermitz
Author-email: ermitz888@gmail.com
License: UNKNOWN
Platform: UNKNOWN
Classifier: Programming Language :: Python
Classifier: License :: OSI Approved :: GNU Lesser General Public License v3 or later (LGPLv3+)
Classifier: Natural Language :: English
Classifier: Operating System :: OS Independent
Classifier: Programming Language :: Python :: 3.5
Classifier: Programming Language :: Python :: 3.6
Classifier: Topic :: Home Automation
Requires-Dist: python-dateutil (==2.7.5)
